ros_configurator/__init__.py
ros_configurator/__version__.py
ros_configurator/functions.py
ros_configurator/ros_parameters.py
ros_configurator/utilities.py
ros_configurator-1.2.2.dist-info/LICENSE
ros_configurator-1.2.2.dist-info/METADATA
ros_configurator-1.2.2.dist-info/WHEEL
ros_configurator-1.2.2.dist-info/entry_points.txt
ros_configurator-1.2.2.dist-info/top_level.txt
ros_configurator-1.2.2.dist-info/RECORD
