Metadata-Version: 2.1
Name: ros-configurator
Version: 1.2.2
Summary: Ros Configurator
Home-page: https://github.com/micheleantonazzi/ros_configurator
Author: Michele Antonazzi
Author-email: micheleantonazzi@gmail.com
License: MIT
Platform: UNKNOWN
Classifier: Development Status :: 3 - Alpha
Classifier: License :: OSI Approved :: MIT License
Classifier: Programming Language :: Python :: 3
Requires-Dist: pathlib
Requires-Dist: sockets
Requires-Dist: termcolor
Requires-Dist: regex
Provides-Extra: test
Requires-Dist: pytest ; extra == 'test'
Requires-Dist: pytest-cov ; extra == 'test'
